paperpython/__init__.py
paperpython/__main__.py
paperpython/communication.py
paperpython/wsgi.py
paperpython/wsgiImporter.py
paperpython/wsgi_pb2.py
paperpython-0.0.3.dist-info/LICENCE
paperpython-0.0.3.dist-info/METADATA
paperpython-0.0.3.dist-info/WHEEL
paperpython-0.0.3.dist-info/top_level.txt
paperpython-0.0.3.dist-info/RECORD
