Metadata-Version: 2.1
Name: paperpython
Version: 0.0.3
Summary: A WSGI compatible server aimed to be used with paperServer
Home-page: https://github.com/SagaraBattousai/paperPython
Author: SagaraBattousai
Author-email: jamesafcalo@gmail.com
License: UNKNOWN
Platform: UNKNOWN
Classifier: Programming Language :: Python :: 3
Classifier: License :: OSI Approved :: GNU Lesser General Public License v3 (LGPLv3)
Classifier: Operating System :: OS Independent
Requires-Python: >=3.5
